yqxx/__init__.py
yqxx/__main__.py
yqxx/yqxx.py
yqxx-0.8.2.dist-info/LICENSE
yqxx-0.8.2.dist-info/METADATA
yqxx-0.8.2.dist-info/WHEEL
yqxx-0.8.2.dist-info/entry_points.txt
yqxx-0.8.2.dist-info/top_level.txt
yqxx-0.8.2.dist-info/RECORD
