Metadata-Version: 2.1
Name: yqxx
Version: 0.8.2
Summary: Auto submitter for xg.hit.edu.cn yqxx
Home-page: https://github.com/lidongj/yqxx
Author: lidongj
Author-email: lidongj@protonmail.com
License: UNKNOWN
Project-URL: Bug Reports, https://github.com/lidongj/yqxx/issues
Project-URL: Source, https://github.com/lidongj/yqxx/
Keywords: Harbin Institute of Technology,HIT,requests
Platform: UNKNOWN
Classifier: Development Status :: 2 - Pre-Alpha
Classifier: Intended Audience :: Developers
Classifier: License :: OSI Approved :: GNU Affero General Public License v3 or later (AGPLv3+)
Classifier: Natural Language :: Chinese (Simplified)
Classifier: Natural Language :: English
Classifier: Operating System :: MacOS
Classifier: Operating System :: Microsoft :: Windows
Classifier: Operating System :: POSIX :: Linux
Classifier: Programming Language :: Python :: 3
Classifier: Programming Language :: Python :: 3.5
Classifier: Programming Language :: Python :: 3.6
Classifier: Programming Language :: Python :: 3.7
Classifier: Programming Language :: Python :: 3.8
Classifier: Programming Language :: Python :: 3 :: Only
Classifier: Topic :: Utilities
Requires-Python: >=3.5, <4
Requires-Dist: PyYAML
Requires-Dist: beautifulsoup4
Requires-Dist: hitutil
Requires-Dist: pycryptodome
Requires-Dist: requests
